README.md
setup.cfg
setup.py
distributions/Binomialdistribution.py
distributions/Gaussiandistribution.py
distributions/Generaldistribution.py
distributions/__init__.py
niklas_distributions.egg-info/PKG-INFO
niklas_distributions.egg-info/SOURCES.txt
niklas_distributions.egg-info/dependency_links.txt
niklas_distributions.egg-info/not-zip-safe
niklas_distributions.egg-info/top_level.txt